{
    "webServerPort": 8081,
    "rpcListenIp": "172.16.23.134",
    "rpcListenPort": 9090,
    "rpcListenPortBin": 9091,
    "daemons": {
        "Funk-Zuhause": {
            "type": "BidCos-RF",
            "ip": "172.16.23.3",
            "port": 2001,
            "isCcu": true,
            "init": true
        },
        "Wired-Zuhause": {
            "type": "BidCos-Wired",
            "ip": "172.16.23.3",
            "port": 2000,
            "isCcu": true,
            "init": true
        },
        "CUxD-Zuhause": {
            "type": "CUxD",
            "ip": "172.16.23.3",
            "port": 8701,
            "isCcu": true,
            "init": true
        },
        "Funk-Büro": {
            "type": "BidCos-RF",
            "ip": "10.0.12.5",
            "port": 2001,
            "isCcu": false
        }
    },
    "datastorePath": "datastore/",
    "language": "de"
}