{
  "0": {
    "params": {},
    "options": {},
    "name": "expert"
  },
  "1": {
    "params": {
      "LONG_ACTION_TYPE": {
        "readonly": true,
        "val": "1"
      },
      "LONG_JT_OFF": {
        "readonly": true,
        "val": "0"
      },
      "LONG_JT_OFFDELAY": {
        "readonly": true,
        "val": "3"
      },
      "LONG_JT_ON": {
        "readonly": true,
        "val": "2"
      },
      "LONG_JT_ONDELAY": {
        "readonly": true,
        "val": "1"
      },
      "LONG_MULTIEXECUTE": {
        "readonly": true,
        "val": "1"
      },
      "LONG_OFFDELAY_TIME": {
        "val": "0.000000"
      },
      "LONG_OFF_TIME": {
        "val": "16383000.000000"
      },
      "LONG_OFF_TIME_MODE": {
        "readonly": true,
        "val": "1"
      },
      "LONG_ONDELAY_TIME": {
        "val": "0.000000"
      },
      "LONG_ON_TIME": {
        "val": "16383000.000000"
      },
      "LONG_ON_TIME_MODE": {
        "readonly": true,
        "val": "1"
      },
      "LONG_TOGGLE_USE": {
        "readonly": true,
        "val": "0"
      },
      "SHORT_ACTION_TYPE": {
        "readonly": true,
        "val": "1"
      },
      "SHORT_JT_OFF": {
        "readonly": true,
        "val": "0"
      },
      "SHORT_JT_OFFDELAY": {
        "readonly": true,
        "val": "3"
      },
      "SHORT_JT_ON": {
        "readonly": true,
        "val": "2"
      },
      "SHORT_JT_ONDELAY": {
        "readonly": true,
        "val": "1"
      },
      "SHORT_OFFDELAY_TIME": {
        "val": "0.000000"
      },
      "SHORT_OFF_TIME": {
        "val": "16383000.000000"
      },
      "SHORT_OFF_TIME_MODE": {
        "readonly": true,
        "val": "1"
      },
      "SHORT_ONDELAY_TIME": {
        "val": "0.000000"
      },
      "SHORT_ON_TIME": {
        "val": "16383000.000000"
      },
      "SHORT_ON_TIME_MODE": {
        "readonly": true,
        "val": "1"
      },
      "SHORT_TOGGLE_USE": {
        "readonly": true,
        "val": "0"
      },
      "UI_DESCRIPTION": {
        "readonly": true,
        "val": "Mit einem kurzen oder langen Tastendruck wird der Schalter f&uuml;r die gew&uuml;nschte Zeit je nach aktuellem Zustand ein- oder ausgeschaltet (Togglefunktion). Ist eine Ein- oder Ausschaltverz&ouml;gerungszeit eingestellt, so wird der Schalter erst nach Ablauf dieser Zeit ein- bzw. ausgeschaltet."
      },
      "UI_TEMPLATE": {
        "readonly": true,
        "val": "$PROFILE_1(UI_DESCRIPTION)"
      },
      "UI_HINT": {
        "readonly": true,
        "val": "1"
      }
    },
    "options": {
      "1": {
        "desc": "ONDELAY_TIME",
        "option": "DELAY",
        "combo": [
          "SHORT_ONDELAY_TIME",
          "LONG_ONDELAY_TIME"
        ],
        "input": "EnterTime_h_m_s",
        "param": "SHORT_ONDELAY_TIME"
      },
      "2": {
        "desc": "ON_TIME",
        "option": "LENGTH_OF_STAY",
        "combo": [
          "SHORT_ON_TIME",
          "LONG_ON_TIME"
        ],
        "input": "EnterTime_h_m_s",
        "param": "SHORT_ON_TIME"
      },
      "3": {
        "desc": "OFFDELAY_TIME",
        "option": "DELAY",
        "combo": [
          "SHORT_OFFDELAY_TIME",
          "LONG_OFFDELAY_TIME"
        ],
        "input": "EnterTime_h_m_s",
        "param": "SHORT_OFFDELAY_TIME"
      },
      "4": {
        "desc": "OFF_TIME",
        "option": "LENGTH_OF_STAY",
        "combo": [
          "SHORT_OFF_TIME",
          "LONG_OFF_TIME"
        ],
        "input": "EnterTime_h_m_s",
        "param": "SHORT_OFF_TIME"
      }
    },
    "name": "switch_on_off"
  },
  "2": {
    "params": {
      "LONG_ACTION_TYPE": {
        "readonly": true,
        "val": "1"
      },
      "LONG_JT_OFF": {
        "readonly": true,
        "val": "0"
      },
      "LONG_JT_OFFDELAY": {
        "readonly": true,
        "val": "1"
      },
      "LONG_JT_ON": {
        "readonly": true,
        "val": "1"
      },
      "LONG_JT_ONDELAY": {
        "readonly": true,
        "val": "1"
      },
      "LONG_MULTIEXECUTE": {
        "readonly": true,
        "val": "1"
      },
      "LONG_OFFDELAY_TIME": {
        "readonly": true,
        "val": "0.000000"
      },
      "LONG_OFF_TIME": {
        "readonly": true,
        "val": "16383000.000000"
      },
      "LONG_OFF_TIME_MODE": {
        "readonly": true,
        "val": "1"
      },
      "LONG_ONDELAY_TIME": {
        "readonly": true,
        "val": "0.000000"
      },
      "LONG_ON_TIME": {
        "val": "300.000000"
      },
      "LONG_ON_TIME_MODE": {
        "readonly": true,
        "val": "1"
      },
      "LONG_TOGGLE_USE": {
        "readonly": true,
        "val": "0"
      },
      "SHORT_ACTION_TYPE": {
        "readonly": true,
        "val": "1"
      },
      "SHORT_JT_OFF": {
        "readonly": true,
        "val": "0"
      },
      "SHORT_JT_OFFDELAY": {
        "readonly": true,
        "val": "1"
      },
      "SHORT_JT_ON": {
        "readonly": true,
        "val": "1"
      },
      "SHORT_JT_ONDELAY": {
        "readonly": true,
        "val": "1"
      },
      "SHORT_OFFDELAY_TIME": {
        "readonly": true,
        "val": "0.000000"
      },
      "SHORT_OFF_TIME": {
        "readonly": true,
        "val": "16383000.000000"
      },
      "SHORT_OFF_TIME_MODE": {
        "readonly": true,
        "val": "1"
      },
      "SHORT_ONDELAY_TIME": {
        "readonly": true,
        "val": "0.000000"
      },
      "SHORT_ON_TIME": {
        "val": "300.000000"
      },
      "SHORT_ON_TIME_MODE": {
        "readonly": true,
        "val": "1"
      },
      "SHORT_TOGGLE_USE": {
        "readonly": true,
        "val": "0"
      },
      "UI_DESCRIPTION": {
        "readonly": true,
        "val": "Mit einem kurzen oder langen Tastendruck schaltet der Schalter f&uuml;r die gew&uuml;nschte Zeit ein. Wird der Taster w&auml;hrend der EIN-Phase nochmal bet&auml;tigt, beginnt die Zeitz&auml;hlung von vorne."
      },
      "UI_TEMPLATE": {
        "readonly": true,
        "val": "$PROFILE_2(UI_DESCRIPTION)"
      },
      "UI_HINT": {
        "readonly": true,
        "val": "2"
      }
    },
    "options": {
      "1": {
        "desc": "ON_TIME",
        "option": "STAIRCASE",
        "combo": [
          "SHORT_ON_TIME",
          "LONG_ON_TIME"
        ],
        "input": "EnterTime_h_m_s",
        "param": "SHORT_ON_TIME"
      }
    },
    "name": "light_stairway"
  },
  "3": {
    "params": {
      "LONG_ACTION_TYPE": {
        "readonly": true,
        "val": "1"
      },
      "LONG_JT_OFF": {
        "readonly": true,
        "val": "0"
      },
      "LONG_JT_OFFDELAY": {
        "readonly": true,
        "val": "1"
      },
      "LONG_JT_ON": {
        "readonly": true,
        "val": "1"
      },
      "LONG_JT_ONDELAY": {
        "readonly": true,
        "val": "1"
      },
      "LONG_MULTIEXECUTE": {
        "readonly": true,
        "val": "1"
      },
      "LONG_OFFDELAY_TIME": {
        "readonly": true,
        "val": "0.000000"
      },
      "LONG_OFF_TIME": {
        "readonly": true,
        "val": "16383000.000000"
      },
      "LONG_OFF_TIME_MODE": {
        "readonly": true,
        "val": "1"
      },
      "LONG_ONDELAY_TIME": {
        "val": "0.000000"
      },
      "LONG_ON_TIME": {
        "val": "16383000.000000"
      },
      "LONG_ON_TIME_MODE": {
        "readonly": true,
        "val": "1"
      },
      "LONG_TOGGLE_USE": {
        "readonly": true,
        "val": "0"
      },
      "SHORT_ACTION_TYPE": {
        "readonly": true,
        "val": "1"
      },
      "SHORT_JT_OFF": {
        "readonly": true,
        "val": "0"
      },
      "SHORT_JT_OFFDELAY": {
        "readonly": true,
        "val": "1"
      },
      "SHORT_JT_ON": {
        "readonly": true,
        "val": "1"
      },
      "SHORT_JT_ONDELAY": {
        "readonly": true,
        "val": "1"
      },
      "SHORT_OFFDELAY_TIME": {
        "readonly": true,
        "val": "0.000000"
      },
      "SHORT_OFF_TIME": {
        "readonly": true,
        "val": "16383000.000000"
      },
      "SHORT_OFF_TIME_MODE": {
        "readonly": true,
        "val": "1"
      },
      "SHORT_ONDELAY_TIME": {
        "val": "0.000000"
      },
      "SHORT_ON_TIME": {
        "val": "16383000.000000"
      },
      "SHORT_ON_TIME_MODE": {
        "readonly": true,
        "val": "1"
      },
      "SHORT_TOGGLE_USE": {
        "readonly": true,
        "val": "0"
      },
      "UI_DESCRIPTION": {
        "readonly": true,
        "val": "Mit einem kurzen oder langen Tastendruck wird der Schalter f&uuml;r die gew&uuml;nschte Zeit eingeschaltet. Ist eine Einschaltverz&ouml;gerungszeit eingestellt, so wird der Schalter erst nach Ablauf dieser Zeit eingeschaltet."
      },
      "UI_TEMPLATE": {
        "readonly": true,
        "val": "$PROFILE_3(UI_DESCRIPTION)"
      },
      "UI_HINT": {
        "readonly": true,
        "val": "3"
      }
    },
    "options": {
      "1": {
        "desc": "ONDELAY_TIME",
        "option": "DELAY",
        "combo": [
          "SHORT_ONDELAY_TIME",
          "LONG_ONDELAY_TIME"
        ],
        "input": "EnterTime_h_m_s",
        "param": "SHORT_ONDELAY_TIME"
      },
      "2": {
        "desc": "ON_TIME",
        "option": "LENGTH_OF_STAY",
        "combo": [
          "SHORT_ON_TIME",
          "LONG_ON_TIME"
        ],
        "input": "EnterTime_h_m_s",
        "param": "SHORT_ON_TIME"
      }
    },
    "name": "switch_on"
  },
  "4": {
    "params": {
      "LONG_ACTION_TYPE": {
        "readonly": true,
        "val": "1"
      },
      "LONG_JT_OFF": {
        "readonly": true,
        "val": "3"
      },
      "LONG_JT_OFFDELAY": {
        "readonly": true,
        "val": "3"
      },
      "LONG_JT_ON": {
        "readonly": true,
        "val": "2"
      },
      "LONG_JT_ONDELAY": {
        "readonly": true,
        "val": "3"
      },
      "LONG_MULTIEXECUTE": {
        "readonly": true,
        "val": "1"
      },
      "LONG_OFFDELAY_TIME": {
        "val": "0.000000"
      },
      "LONG_OFF_TIME": {
        "val": "16383000.000000"
      },
      "LONG_OFF_TIME_MODE": {
        "readonly": true,
        "val": "1"
      },
      "LONG_ONDELAY_TIME": {
        "readonly": true,
        "val": "0.000000"
      },
      "LONG_ON_TIME": {
        "readonly": true,
        "val": "16383000.000000"
      },
      "LONG_ON_TIME_MODE": {
        "readonly": true,
        "val": "1"
      },
      "LONG_TOGGLE_USE": {
        "readonly": true,
        "val": "0"
      },
      "SHORT_ACTION_TYPE": {
        "readonly": true,
        "val": "1"
      },
      "SHORT_JT_OFF": {
        "readonly": true,
        "val": "3"
      },
      "SHORT_JT_OFFDELAY": {
        "readonly": true,
        "val": "3"
      },
      "SHORT_JT_ON": {
        "readonly": true,
        "val": "2"
      },
      "SHORT_JT_ONDELAY": {
        "readonly": true,
        "val": "3"
      },
      "SHORT_OFFDELAY_TIME": {
        "val": "0.000000"
      },
      "SHORT_OFF_TIME": {
        "val": "16383000.000000"
      },
      "SHORT_OFF_TIME_MODE": {
        "readonly": true,
        "val": "1"
      },
      "SHORT_ONDELAY_TIME": {
        "readonly": true,
        "val": "0.000000"
      },
      "SHORT_ON_TIME": {
        "readonly": true,
        "val": "16383000.000000"
      },
      "SHORT_ON_TIME_MODE": {
        "readonly": true,
        "val": "1"
      },
      "SHORT_TOGGLE_USE": {
        "readonly": true,
        "val": "0"
      },
      "UI_DESCRIPTION": {
        "readonly": true,
        "val": "Mit einem kurzen oder langen Tastendruck wird der Schalter f&uuml;r die gew&uuml;nschte Zeit ausgeschaltet. Ist eine Ausschaltverz&ouml;gerungszeit eingestellt, so wird der Schalter erst nach Ablauf dieser Zeit ausgeschaltet."
      },
      "UI_TEMPLATE": {
        "readonly": true,
        "val": "$PROFILE_4(UI_DESCRIPTION)"
      },
      "UI_HINT": {
        "readonly": true,
        "val": "4"
      }
    },
    "options": {
      "1": {
        "desc": "OFFDELAY_TIME",
        "option": "DELAY",
        "combo": [
          "SHORT_OFFDELAY_TIME",
          "LONG_OFFDELAY_TIME"
        ],
        "input": "EnterTime_h_m_s",
        "param": "SHORT_OFFDELAY_TIME"
      },
      "2": {
        "desc": "OFF_TIME",
        "option": "LENGTH_OF_STAY",
        "combo": [
          "SHORT_OFF_TIME",
          "LONG_OFF_TIME"
        ],
        "input": "EnterTime_h_m_s",
        "param": "SHORT_OFF_TIME"
      }
    },
    "name": "switch_off"
  }
}